bases/__init__.py
bases/py.typed
bases/random.py
bases/alphabet/__init__.py
bases/alphabet/abstract.py
bases/alphabet/range_alphabet.py
bases/alphabet/string_alphabet.py
bases/encoding/__init__.py
bases/encoding/base.py
bases/encoding/block.py
bases/encoding/errors.py
bases/encoding/fixchar.py
bases/encoding/simple.py
bases/encoding/zeropad.py
bases-0.3.0.dist-info/LICENSE
bases-0.3.0.dist-info/METADATA
bases-0.3.0.dist-info/WHEEL
bases-0.3.0.dist-info/top_level.txt
bases-0.3.0.dist-info/RECORD
